vq/__init__.py
vq/activations.py
vq/blocks.py
vq/bs_roformer5.py
vq/codec_decoder.py
vq/codec_decoder_vocos.py
vq/codec_encoder.py
vq/factorized_vector_quantize.py
vq/module.py
vq/residual_vq.py
vq/unet.py
vq/alias_free_torch/__init__.py
vq/alias_free_torch/act.py
vq/alias_free_torch/filter.py
vq/alias_free_torch/resample.py
xcodec2/__init__.py
xcodec2/configuration_bigcodec.py
xcodec2/modeling_xcodec2.py
xcodec2_infer_lib-0.1.1.dist-info/LICENSE
xcodec2_infer_lib-0.1.1.dist-info/METADATA
xcodec2_infer_lib-0.1.1.dist-info/WHEEL
xcodec2_infer_lib-0.1.1.dist-info/top_level.txt
xcodec2_infer_lib-0.1.1.dist-info/RECORD
