Metadata-Version: 2.2
Name: xcodec2-infer-lib
Version: 0.1.1
Summary: Trying to achieve M chip Macbook support for https://huggingface.co/HKUSTAudio/xcodec2.
Author: Utku Ege Tuluk
License: Creative Commons Attribution 4.0 International (CC BY 4.0)
Project-URL: homepage, https://github.com/uetuluk/xcodec2-infer-lib
Classifier: Programming Language :: Python :: 3
Classifier: Programming Language :: Python :: 3.12
Classifier: Operating System :: OS Independent
Requires-Python: >=3.12
License-File: LICENSE
Requires-Dist: torch==2.4.1
Requires-Dist: numpy==2.0.2
Requires-Dist: einops==0.8.0
Requires-Dist: transformers==4.46.1
Requires-Dist: rotary-embedding-torch==0.8.6
Requires-Dist: vector-quantize-pytorch==1.21.7
Provides-Extra: dev
Requires-Dist: pytest; extra == "dev"
Requires-Dist: safetensors; extra == "dev"
